README.rst
setup.py
maildocker/__init__.py
maildocker/maildocker.py
maildocker/message.py
maildocker/version.py
maildocker.egg-info/PKG-INFO
maildocker.egg-info/SOURCES.txt
maildocker.egg-info/dependency_links.txt
maildocker.egg-info/top_level.txt