Metadata-Version: 1.0
Name: maildocker
Version: 1.0.1
Summary: Maildocker library for Python
Home-page: UNKNOWN
Author: UNKNOWN
Author-email: UNKNOWN
License: UNKNOWN
Platform: UNKNOWN
